imseqvis/__init__.py
imseqvis/__main__.py
imseqvis/control_widget.py
imseqvis/image_viewer.py
imseqvis/sequence_viewer.py
imseqvis-0.2.8.dist-info/licenses/LICENSE
imseqvis-0.2.8.dist-info/METADATA
imseqvis-0.2.8.dist-info/WHEEL
imseqvis-0.2.8.dist-info/top_level.txt
imseqvis-0.2.8.dist-info/RECORD
