Metadata-Version: 2.4
Name: imseqvis
Version: 0.2.8
Summary: A Qt-based image sequence visualizer widget
Author-email: snototter <snototter@users.noreply.github.com>
License: MIT License
Project-URL: homepage, https://github.com/snototter/imseqvis
Classifier: Development Status :: 3 - Alpha
Classifier: Intended Audience :: Developers
Classifier: License :: OSI Approved :: MIT License
Classifier: Programming Language :: Python :: 3
Classifier: Programming Language :: Python :: 3 :: Only
Requires-Python: >=3.7
License-File: LICENSE
Requires-Dist: natsort
Requires-Dist: numpy
Requires-Dist: qimage2ndarray
Requires-Dist: qtpy
Requires-Dist: vito
Provides-Extra: pyqt5
Requires-Dist: PyQt5; extra == "pyqt5"
Provides-Extra: pyqt6
Requires-Dist: PyQt6; extra == "pyqt6"
Provides-Extra: pyside2
Requires-Dist: PySide2; extra == "pyside2"
Provides-Extra: pyside6
Requires-Dist: PySide6; extra == "pyside6"
Dynamic: license-file
